krules_cloudevents/.gitignore
krules_cloudevents/__init__.py
krules_cloudevents/route/__init__.py
krules_cloudevents/route/dispatcher.py
krules_cloudevents/test_dispatcher.py
krules_dispatcher_cloudevents-0.12.0.dist-info/AUTHORS
krules_dispatcher_cloudevents-0.12.0.dist-info/METADATA
krules_dispatcher_cloudevents-0.12.0.dist-info/WHEEL
krules_dispatcher_cloudevents-0.12.0.dist-info/RECORD
