Metadata-Version: 2.1
Name: krules-dispatcher-cloudevents
Version: 0.12.0
Summary: KRules cloudevents dispatcher
Home-page: https://github.com/airspot-dev/krules
License: Apache Licence 2.0
Author: Alberto Degli Esposti
Author-email: alberto@arispot.tech
Requires-Python: >=3.11,<3.12
Classifier: Development Status :: 3 - Alpha
Classifier: License :: OSI Approved :: Apache Software License
Classifier: License :: Other/Proprietary License
Classifier: Programming Language :: Python :: 3
Classifier: Programming Language :: Python :: 3.11
Requires-Dist: cloudevents (>=1.10.1,<2.0.0)
Requires-Dist: krules-core (>=0.12.0,<0.13.0)
Requires-Dist: pytz (>=2024.1,<2025.0)
Project-URL: Repository, https://github.com/airspot-dev/krules
